{
    "patterns": "",
    "custom-icons-classes": "",
    "custom-icons-css": "",
    "brand-color": "#ff0000",
    "accent-1-color": "#00ff00",
    "accent-2-color": "#0000ff",
    "google-fonts": "Poppins:300,400,500,600,700",
    "prefix": "azen",
    "container-widths": "768px:750px\r\n992px:970px\r\n1200px:1170px",
    "tags": {
        "jobook/tabs.htm": "tabs",
        "jobook/menu.html": "menu",
        "jobook/tabs-1.htm": "tabs",
        "jobook/tabs-2.htm": "tabs",
        "jobook/tabs-3.htm": "tabs",
        "jobook/feature.htm": "",
        "jobook/menu-2.html": "menu",
        "jobook/menu-3.html": "menu",
        "jobook/middle.html": "",
        "jobook/counters.htm": "",
        "jobook/isotope.html": "gallery",
        "jobook/features.html": "",
        "jobook/header-1.html": "header",
        "jobook/header-2.html": "header",
        "jobook/header-3.html": "header",
        "jobook/icon-text.htm": "",
        "jobook/middle-2.html": "header",
        "jobook/middle-3.html": "header",
        "jobook/portfolio.htm": "",
        "jobook/circle-bar.htm": "",
        "jobook/counters-2.htm": "",
        "jobook/skill-line.htm": "",
        "jobook/accordion-1.htm": "accordion",
        "jobook/accordion-2.htm": "accordion",
        "jobook/get-jobook.html": "",
        "jobook/jobook-text.htm": "text",
        "jobook/map-section.html": "google-map",
        "jobook/social-icons.htm": "",
        "jobook/get-jobook-2.html": "",
        "jobook/video-section.html": "",
        "jobook/call-to-action.html": "call-to-action",
        "jobook/pricing-table-1.htm": "price",
        "jobook/pricing-table-2.htm": "price",
        "jobook/pricing-table-3.htm": "price",
        "jobook/column-icon-link.htm": "",
        "jobook/latest-projects.html": "",
        "jobook/phone-mail-logos.htm": "",
        "jobook/video-section-2.html": "video",
        "jobook/content-read-more.htm": "",
        "jobook/slider-companies.html": "slider",
        "jobook/slider-candidates.html": "slider",
        "jobook/companies-we-helped.html": "",
        "jobook/under-footer-element.htm": "",
        "jobook/under-footer-section.html": "footer",
        "jobook/footer-section-wrapper.html": "footer",
        "jobook/header-section-wrapper.html": "header",
        "jobook/inspiring-business-performance.html": ""
    },
    "child-suggestions": {
        "forms/form-container.htm": [
            "jobook/forms/input-field.htm",
            "jobook/forms/dropdown-list.htm",
            "jobook/forms/big-text-field.htm",
            "jobook/forms/form-container.htm",
            "jobook/forms/input-field-footer.htm"
        ]
    },
    "elements-widths": {
    }
}
